sasctl/__init__.py
sasctl/__main__.py
sasctl/core.py
sasctl/exceptions.py
sasctl/services.py
sasctl/tasks.py
sasctl/_services/__init__.py
sasctl/_services/cas_management.py
sasctl/_services/concepts.py
sasctl/_services/data_sources.py
sasctl/_services/files.py
sasctl/_services/folders.py
sasctl/_services/microanalytic_score.py
sasctl/_services/model_management.py
sasctl/_services/model_publish.py
sasctl/_services/model_repository.py
sasctl/_services/projects.py
sasctl/_services/relationships.py
sasctl/_services/report_images.py
sasctl/_services/reports.py
sasctl/_services/saslogon.py
sasctl/_services/score_definitions.py
sasctl/_services/score_execution.py
sasctl/_services/sentiment_analysis.py
sasctl/_services/service.py
sasctl/_services/text_categorization.py
sasctl/_services/text_parsing.py
sasctl/_services/workflow.py
sasctl/pzmm/__init__.py
sasctl/pzmm/git_integration.py
sasctl/pzmm/import_model.py
sasctl/pzmm/mlflow_model.py
sasctl/pzmm/model_parameters.py
sasctl/pzmm/pickle_model.py
sasctl/pzmm/write_json_files.py
sasctl/pzmm/write_score_code.py
sasctl/pzmm/zip_model.py
sasctl/pzmm/template_files/dmcas_fitstat.json
sasctl/pzmm/template_files/dmcas_lift.json
sasctl/pzmm/template_files/dmcas_misc.json
sasctl/pzmm/template_files/dmcas_relativeimportance.json
sasctl/pzmm/template_files/dmcas_roc.json
sasctl/pzmm/template_files/clf_jsons/groupMetrics.json
sasctl/pzmm/template_files/clf_jsons/maxDifferences.json
sasctl/pzmm/template_files/reg_jsons/groupMetrics.json
sasctl/pzmm/template_files/reg_jsons/maxDifferences.json
sasctl/utils/__init__.py
sasctl/utils/astore.py
sasctl/utils/cli.py
sasctl/utils/decorators.py
sasctl/utils/misc.py
sasctl/utils/model_info.py
sasctl/utils/model_migration.py
sasctl/utils/pymas/__init__.py
sasctl/utils/pymas/core.py
sasctl/utils/pymas/ds2.py
sasctl/utils/pymas/python.py
sasctl/utils/pyml2ds/__init__.py
sasctl/utils/pyml2ds/core.py
sasctl/utils/pyml2ds/basic/__init__.py
sasctl/utils/pyml2ds/basic/tree.py
sasctl-1.11.5.dist-info/licenses/LICENSE
sasctl-1.11.5.dist-info/METADATA
sasctl-1.11.5.dist-info/WHEEL
sasctl-1.11.5.dist-info/entry_points.txt
sasctl-1.11.5.dist-info/top_level.txt
sasctl-1.11.5.dist-info/RECORD
