Metadata-Version: 2.4
Name: sasctl
Version: 1.11.5
Summary: SAS Viya Python Client
Home-page: https://github.com/sassoftware/python-sasctl/
Author: SAS
License: Apache v2.0
Project-URL: Bug Tracker, https://github.com/sassoftware/python-sasctl/issues
Project-URL: Documentation, https://sassoftware.github.io/python-sasctl/
Project-URL: Source Code, https://github.com/sassoftware/python-sasctl
Classifier: Development Status :: 5 - Production/Stable
Classifier: License :: OSI Approved :: Apache Software License
Classifier: Environment :: Console
Classifier: Intended Audience :: Science/Research
Classifier: Intended Audience :: Developers
Classifier: Programming Language :: Python
Classifier: Programming Language :: Python :: 3
Classifier: Programming Language :: Python :: 3.6
Classifier: Programming Language :: Python :: 3.7
Classifier: Programming Language :: Python :: 3.8
Classifier: Programming Language :: Python :: 3.9
Classifier: Programming Language :: Python :: 3.10
Classifier: Topic :: Software Development
Classifier: Topic :: Scientific/Engineering
Classifier: Operating System :: OS Independent
Requires-Python: >=3.6
License-File: LICENSE
Requires-Dist: dill
Requires-Dist: pandas>=0.24.0
Requires-Dist: requests
Requires-Dist: pyyaml
Requires-Dist: packaging
Provides-Extra: swat
Requires-Dist: swat; extra == "swat"
Provides-Extra: gitpython
Requires-Dist: GitPython; extra == "gitpython"
Provides-Extra: scikit-learn
Requires-Dist: scikit-learn; extra == "scikit-learn"
Provides-Extra: kerberos
Requires-Dist: kerberos; platform_system != "Windows" and extra == "kerberos"
Requires-Dist: winkerberos; platform_system == "Windows" and extra == "kerberos"
Provides-Extra: all
Requires-Dist: swat; extra == "all"
Requires-Dist: GitPython; extra == "all"
Requires-Dist: kerberos; platform_system != "Windows" and extra == "all"
Requires-Dist: winkerberos; platform_system == "Windows" and extra == "all"
Dynamic: author
Dynamic: classifier
Dynamic: description
Dynamic: description-content-type
Dynamic: home-page
Dynamic: license
Dynamic: license-file
Dynamic: project-url
Dynamic: provides-extra
Dynamic: requires-dist
Dynamic: requires-python
Dynamic: summary
